setup.py
LearnUdacitydistributions.egg-info/PKG-INFO
LearnUdacitydistributions.egg-info/SOURCES.txt
LearnUdacitydistributions.egg-info/dependency_links.txt
LearnUdacitydistributions.egg-info/not-zip-safe
LearnUdacitydistributions.egg-info/top_level.txt
distributions/Binomialdistribution.py
distributions/Gaussiandistribution.py
distributions/Generaldistribution.py
distributions/__init__.py