Metadata-Version: 1.0
Name: LearnUdacitydistributions
Version: 0.1
Summary: Gaussian distributions
Home-page: UNKNOWN
Author: Tobias Mueller
Author-email: tobias3m@googlemail.com
License: UNKNOWN
Platform: UNKNOWN
